{
  "swagger": "2.0",
  "info": {
    "title": "npool/thirdlogingateway/thirdlogingateway.proto",
    "version": "version not set"
  },
  "consumes": [
    "application/json"
  ],
  "produces": [
    "application/json"
  ],
  "paths": {
    "/v1/create/app/auth": {
      "post": {
        "operationId": "ThirdLoginGateway_CreateAppAuth",
        "responses": {
          "200": {
            "description": "A successful response.",
            "schema": {
              "$ref": "#/definitions/v1CreateAppAuthResponse"
            }
          },
          "default": {
            "description": "An unexpected error response.",
            "schema": {
              "$ref": "#/definitions/runtimeError"
            }
          }
        },
        "parameters": [
          {
            "name": "body",
            "in": "body",
            "required": true,
            "schema": {
              "$ref": "#/definitions/v1CreateAppAuthRequest"
            }
          }
        ],
        "tags": [
          "ThirdLoginGateway"
        ]
      }
    },
    "/v1/create/app/auths": {
      "post": {
        "operationId": "ThirdLoginGateway_CreateAppAuths",
        "responses": {
          "200": {
            "description": "A successful response.",
            "schema": {
              "$ref": "#/definitions/v1CreateAppAuthsResponse"
            }
          },
          "default": {
            "description": "An unexpected error response.",
            "schema": {
              "$ref": "#/definitions/runtimeError"
            }
          }
        },
        "parameters": [
          {
            "name": "body",
            "in": "body",
            "required": true,
            "schema": {
              "$ref": "#/definitions/v1CreateAppAuthsRequest"
            }
          }
        ],
        "tags": [
          "ThirdLoginGateway"
        ]
      }
    },
    "/v1/create/auth": {
      "post": {
        "operationId": "ThirdLoginGateway_CreateAuth",
        "responses": {
          "200": {
            "description": "A successful response.",
            "schema": {
              "$ref": "#/definitions/v1CreateAuthResponse"
            }
          },
          "default": {
            "description": "An unexpected error response.",
            "schema": {
              "$ref": "#/definitions/runtimeError"
            }
          }
        },
        "parameters": [
          {
            "name": "body",
            "in": "body",
            "required": true,
            "schema": {
              "$ref": "#/definitions/v1CreateAuthRequest"
            }
          }
        ],
        "tags": [
          "ThirdLoginGateway"
        ]
      }
    },
    "/v1/create/auths": {
      "post": {
        "operationId": "ThirdLoginGateway_CreateAuths",
        "responses": {
          "200": {
            "description": "A successful response.",
            "schema": {
              "$ref": "#/definitions/v1CreateAuthsResponse"
            }
          },
          "default": {
            "description": "An unexpected error response.",
            "schema": {
              "$ref": "#/definitions/runtimeError"
            }
          }
        },
        "parameters": [
          {
            "name": "body",
            "in": "body",
            "required": true,
            "schema": {
              "$ref": "#/definitions/v1CreateAuthsRequest"
            }
          }
        ],
        "tags": [
          "ThirdLoginGateway"
        ]
      }
    },
    "/v1/create/third/party": {
      "post": {
        "operationId": "ThirdLoginGateway_CreateThirdParty",
        "responses": {
          "200": {
            "description": "A successful response.",
            "schema": {
              "$ref": "#/definitions/v1CreateThirdPartyResponse"
            }
          },
          "default": {
            "description": "An unexpected error response.",
            "schema": {
              "$ref": "#/definitions/runtimeError"
            }
          }
        },
        "parameters": [
          {
            "name": "body",
            "in": "body",
            "required": true,
            "schema": {
              "$ref": "#/definitions/v1CreateThirdPartyRequest"
            }
          }
        ],
        "tags": [
          "ThirdLoginGateway"
        ]
      }
    },
    "/v1/get/app/auths": {
      "post": {
        "operationId": "ThirdLoginGateway_GetAppAuths",
        "responses": {
          "200": {
            "description": "A successful response.",
            "schema": {
              "$ref": "#/definitions/v1GetAppAuthsResponse"
            }
          },
          "default": {
            "description": "An unexpected error response.",
            "schema": {
              "$ref": "#/definitions/runtimeError"
            }
          }
        },
        "parameters": [
          {
            "name": "body",
            "in": "body",
            "required": true,
            "schema": {
              "$ref": "#/definitions/v1GetAppAuthsRequest"
            }
          }
        ],
        "tags": [
          "ThirdLoginGateway"
        ]
      }
    },
    "/v1/get/auths": {
      "post": {
        "operationId": "ThirdLoginGateway_GetAuths",
        "responses": {
          "200": {
            "description": "A successful response.",
            "schema": {
              "$ref": "#/definitions/v1GetAuthsResponse"
            }
          },
          "default": {
            "description": "An unexpected error response.",
            "schema": {
              "$ref": "#/definitions/runtimeError"
            }
          }
        },
        "parameters": [
          {
            "name": "body",
            "in": "body",
            "required": true,
            "schema": {
              "$ref": "#/definitions/v1GetAuthsRequest"
            }
          }
        ],
        "tags": [
          "ThirdLoginGateway"
        ]
      }
    },
    "/v1/get/third/parties": {
      "post": {
        "operationId": "ThirdLoginGateway_GetThirdParties",
        "responses": {
          "200": {
            "description": "A successful response.",
            "schema": {
              "$ref": "#/definitions/v1GetThirdPartiesResponse"
            }
          },
          "default": {
            "description": "An unexpected error response.",
            "schema": {
              "$ref": "#/definitions/runtimeError"
            }
          }
        },
        "parameters": [
          {
            "name": "body",
            "in": "body",
            "required": true,
            "schema": {
              "$ref": "#/definitions/v1GetThirdPartiesRequest"
            }
          }
        ],
        "tags": [
          "ThirdLoginGateway"
        ]
      }
    },
    "/v1/login": {
      "post": {
        "operationId": "ThirdLoginGateway_Login",
        "responses": {
          "200": {
            "description": "A successful response.",
            "schema": {
              "$ref": "#/definitions/v1LoginResponse"
            }
          },
          "default": {
            "description": "An unexpected error response.",
            "schema": {
              "$ref": "#/definitions/runtimeError"
            }
          }
        },
        "parameters": [
          {
            "name": "body",
            "in": "body",
            "required": true,
            "schema": {
              "$ref": "#/definitions/v1LoginRequest"
            }
          }
        ],
        "tags": [
          "ThirdLoginGateway"
        ]
      }
    },
    "/v1/update/third/party": {
      "post": {
        "operationId": "ThirdLoginGateway_UpdateThirdParty",
        "responses": {
          "200": {
            "description": "A successful response.",
            "schema": {
              "$ref": "#/definitions/v1UpdateThirdPartyResponse"
            }
          },
          "default": {
            "description": "An unexpected error response.",
            "schema": {
              "$ref": "#/definitions/runtimeError"
            }
          }
        },
        "parameters": [
          {
            "name": "body",
            "in": "body",
            "required": true,
            "schema": {
              "$ref": "#/definitions/v1UpdateThirdPartyRequest"
            }
          }
        ],
        "tags": [
          "ThirdLoginGateway"
        ]
      }
    },
    "/version": {
      "post": {
        "summary": "Method Version",
        "operationId": "ThirdLoginGateway_Version",
        "responses": {
          "200": {
            "description": "A successful response.",
            "schema": {
              "$ref": "#/definitions/v1VersionResponse"
            }
          },
          "default": {
            "description": "An unexpected error response.",
            "schema": {
              "$ref": "#/definitions/runtimeError"
            }
          }
        },
        "parameters": [
          {
            "name": "body",
            "in": "body",
            "required": true,
            "schema": {
              "properties": {}
            }
          }
        ],
        "tags": [
          "ThirdLoginGateway"
        ]
      }
    }
  },
  "definitions": {
    "protobufAny": {
      "type": "object",
      "properties": {
        "type_url": {
          "type": "string"
        },
        "value": {
          "type": "string",
          "format": "byte"
        }
      }
    },
    "runtimeError": {
      "type": "object",
      "properties": {
        "error": {
          "type": "string"
        },
        "code": {
          "type": "integer",
          "format": "int32"
        },
        "message": {
          "type": "string"
        },
        "details": {
          "type": "array",
          "items": {
            "$ref": "#/definitions/protobufAny"
          }
        }
      }
    },
    "v1AppRole": {
      "type": "object",
      "properties": {
        "ID": {
          "type": "string"
        },
        "AppID": {
          "type": "string"
        },
        "CreatedBy": {
          "type": "string"
        },
        "Role": {
          "type": "string"
        },
        "Description": {
          "type": "string"
        },
        "Default": {
          "type": "boolean"
        }
      }
    },
    "v1AppUser": {
      "type": "object",
      "properties": {
        "ID": {
          "type": "string"
        },
        "AppID": {
          "type": "string"
        },
        "EmailAddress": {
          "type": "string"
        },
        "PhoneNO": {
          "type": "string"
        },
        "ImportFromApp": {
          "type": "string"
        },
        "CreateAt": {
          "type": "integer",
          "format": "int64"
        }
      }
    },
    "v1AppUserControl": {
      "type": "object",
      "properties": {
        "ID": {
          "type": "string"
        },
        "AppID": {
          "type": "string"
        },
        "UserID": {
          "type": "string"
        },
        "SigninVerifyByGoogleAuthentication": {
          "type": "boolean"
        },
        "GoogleAuthenticationVerified": {
          "type": "boolean"
        }
      }
    },
    "v1AppUserExtra": {
      "type": "object",
      "properties": {
        "ID": {
          "type": "string"
        },
        "AppID": {
          "type": "string"
        },
        "UserID": {
          "type": "string"
        },
        "Username": {
          "type": "string"
        },
        "AddressFields": {
          "type": "array",
          "items": {
            "type": "string"
          }
        },
        "Gender": {
          "type": "string"
        },
        "PostalCode": {
          "type": "string"
        },
        "Age": {
          "type": "integer",
          "format": "int64"
        },
        "Birthday": {
          "type": "integer",
          "format": "int64"
        },
        "Avatar": {
          "type": "string"
        },
        "Organization": {
          "type": "string"
        },
        "FirstName": {
          "type": "string"
        },
        "LastName": {
          "type": "string"
        },
        "IDNumber": {
          "type": "string"
        }
      }
    },
    "v1AppUserInfo": {
      "type": "object",
      "properties": {
        "User": {
          "$ref": "#/definitions/v1AppUser"
        },
        "Extra": {
          "$ref": "#/definitions/v1AppUserExtra"
        },
        "Ctrl": {
          "$ref": "#/definitions/v1AppUserControl"
        },
        "Ban": {
          "$ref": "#/definitions/v1BanAppUser"
        },
        "Roles": {
          "type": "array",
          "items": {
            "$ref": "#/definitions/v1AppRole"
          }
        },
        "SecretMap": {
          "$ref": "#/definitions/v1AppUserSecretMap"
        }
      }
    },
    "v1AppUserSecretMap": {
      "type": "object",
      "properties": {
        "HasGoogleSecret": {
          "type": "boolean"
        }
      }
    },
    "v1Auth": {
      "type": "object",
      "properties": {
        "ID": {
          "type": "string"
        },
        "AppID": {
          "type": "string"
        },
        "ThirdPartyID": {
          "type": "string"
        },
        "AppKey": {
          "type": "string"
        },
        "AppSecret": {
          "type": "string"
        },
        "RedirectURL": {
          "type": "string"
        },
        "AuthURL": {
          "type": "string"
        }
      }
    },
    "v1BanAppUser": {
      "type": "object",
      "properties": {
        "ID": {
          "type": "string"
        },
        "AppID": {
          "type": "string"
        },
        "UserID": {
          "type": "string"
        },
        "Message": {
          "type": "string"
        }
      }
    },
    "v1CreateAppAuthRequest": {
      "type": "object",
      "properties": {
        "TargetAppID": {
          "type": "string"
        },
        "Info": {
          "$ref": "#/definitions/v1Auth"
        }
      }
    },
    "v1CreateAppAuthResponse": {
      "type": "object",
      "properties": {
        "Info": {
          "$ref": "#/definitions/v1Auth"
        }
      }
    },
    "v1CreateAppAuthsRequest": {
      "type": "object",
      "properties": {
        "TargetAppID": {
          "type": "string"
        },
        "Infos": {
          "type": "array",
          "items": {
            "$ref": "#/definitions/v1Auth"
          }
        }
      }
    },
    "v1CreateAppAuthsResponse": {
      "type": "object",
      "properties": {
        "Infos": {
          "type": "array",
          "items": {
            "$ref": "#/definitions/v1Auth"
          }
        }
      }
    },
    "v1CreateAuthRequest": {
      "type": "object",
      "properties": {
        "Info": {
          "$ref": "#/definitions/v1Auth"
        }
      }
    },
    "v1CreateAuthResponse": {
      "type": "object",
      "properties": {
        "Info": {
          "$ref": "#/definitions/v1Auth"
        }
      }
    },
    "v1CreateAuthsRequest": {
      "type": "object",
      "properties": {
        "AppID": {
          "type": "string"
        },
        "Infos": {
          "type": "array",
          "items": {
            "$ref": "#/definitions/v1Auth"
          }
        }
      }
    },
    "v1CreateAuthsResponse": {
      "type": "object",
      "properties": {
        "Infos": {
          "type": "array",
          "items": {
            "$ref": "#/definitions/v1Auth"
          }
        }
      }
    },
    "v1CreateThirdPartyRequest": {
      "type": "object",
      "properties": {
        "Info": {
          "$ref": "#/definitions/v1ThirdParty"
        }
      }
    },
    "v1CreateThirdPartyResponse": {
      "type": "object",
      "properties": {
        "Info": {
          "$ref": "#/definitions/v1ThirdParty"
        }
      }
    },
    "v1GetAppAuthsRequest": {
      "type": "object",
      "properties": {
        "TargetAppID": {
          "type": "string"
        }
      }
    },
    "v1GetAppAuthsResponse": {
      "type": "object",
      "properties": {
        "Infos": {
          "type": "array",
          "items": {
            "$ref": "#/definitions/v1Auth"
          }
        }
      }
    },
    "v1GetAuthsRequest": {
      "type": "object",
      "properties": {
        "AppID": {
          "type": "string"
        }
      }
    },
    "v1GetAuthsResponse": {
      "type": "object",
      "properties": {
        "Infos": {
          "type": "array",
          "items": {
            "$ref": "#/definitions/v1Auth"
          }
        }
      }
    },
    "v1GetThirdPartiesRequest": {
      "type": "object"
    },
    "v1GetThirdPartiesResponse": {
      "type": "object",
      "properties": {
        "Infos": {
          "type": "array",
          "items": {
            "$ref": "#/definitions/v1ThirdParty"
          }
        }
      }
    },
    "v1LoginRequest": {
      "type": "object",
      "properties": {
        "Code": {
          "type": "string"
        },
        "AppID": {
          "type": "string"
        },
        "ThirdPartyID": {
          "type": "string"
        }
      }
    },
    "v1LoginResponse": {
      "type": "object",
      "properties": {
        "Info": {
          "$ref": "#/definitions/v1AppUserInfo"
        }
      }
    },
    "v1ThirdParty": {
      "type": "object",
      "properties": {
        "ID": {
          "type": "string"
        },
        "BrandName": {
          "type": "string"
        },
        "Logo": {
          "type": "string"
        },
        "Domain": {
          "type": "string"
        },
        "AuthBase": {
          "type": "string"
        }
      }
    },
    "v1UpdateThirdPartyRequest": {
      "type": "object",
      "properties": {
        "Info": {
          "$ref": "#/definitions/v1ThirdParty"
        }
      }
    },
    "v1UpdateThirdPartyResponse": {
      "type": "object",
      "properties": {
        "Info": {
          "$ref": "#/definitions/v1ThirdParty"
        }
      }
    },
    "v1VersionResponse": {
      "type": "object",
      "properties": {
        "Info": {
          "type": "string"
        }
      }
    }
  }
}
